<?xml version="1.0" encoding="UTF-8"?>

<!-- generated on Fri Dec  6 16:37:15 2019 by Eclipse SUMO Version 93b75bff
<configuration xmlns:xsi="http://www.w3.org/2001/XMLSchema-instance" xsi:noNamespaceSchemaLocation="http://sumo.dlr.de/xsd/sumoConfiguration.xsd">

    <input>
        <net-file value="network.xml"/>
        <route-files value="routes.xml"/>
        <additional-files value="additional.xml"/>
    </input>

    <time>
        <begin value="0"/>
        <end value="3600"/>
        <step-length value="0.1"/>
    </time>

    <report>
        <duration-log.disable value="true"/>
        <no-step-log value="true"/>
    </report>

    <traci_server>
        <remote-port value="56550"/>
    </traci_server>

    <random_number>
        <random value="true"/>
    </random_number>

    <gui_only>
        <tracker-interval value="0.1"/>
    </gui_only>

</configuration>
-->

<meandata xmlns:xsi="http://www.w3.org/2001/XMLSchema-instance" xsi:noNamespaceSchemaLocation="http://sumo.dlr.de/xsd/meandata_file.xsd">
    <interval begin="0.00" end="300.00" id="ed1">
        <edge id="link1" sampledSeconds="12506.84" traveltime="55.11" overlapTraveltime="55.39" density="41.69" occupancy="6.93" waitingTime="0.00" speed="18.14" departed="249" arrived="0" entered="0" left="207" laneChangedFrom="210" laneChangedTo="210"/>
        <edge id="link2" sampledSeconds="10275.43" traveltime="55.24" overlapTraveltime="55.51" density="34.25" occupancy="5.68" waitingTime="0.00" speed="18.10" departed="0" arrived="0" entered="207" left="163" laneChangedFrom="71" laneChangedTo="71"/>
        <edge id="link3" sampledSeconds="7207.34" traveltime="53.91" overlapTraveltime="54.18" density="24.02" occupancy="3.98" waitingTime="0.00" speed="18.55" departed="0" arrived="0" entered="163" left="118" laneChangedFrom="74" laneChangedTo="74"/>
        <edge id="link4" sampledSeconds="5372.03" traveltime="54.02" overlapTraveltime="54.29" density="17.91" occupancy="2.97" waitingTime="0.00" speed="18.51" departed="0" arrived="0" entered="118" left="68" laneChangedFrom="45" laneChangedTo="45"/>
        <edge id="link5" sampledSeconds="2280.54" traveltime="51.08" overlapTraveltime="51.33" density="7.60" occupancy="1.26" waitingTime="0.00" speed="19.58" departed="0" arrived="20" entered="68" left="0" laneChangedFrom="29" laneChangedTo="29"/>
    </interval>
    <interval begin="300.00" end="600.00" id="ed1">
        <edge id="link1" sampledSeconds="12790.16" traveltime="54.12" overlapTraveltime="54.39" density="42.63" occupancy="7.09" waitingTime="0.00" speed="18.48" departed="234" arrived="0" entered="0" left="232" laneChangedFrom="201" laneChangedTo="201"/>
        <edge id="link2" sampledSeconds="12735.95" traveltime="54.26" overlapTraveltime="54.53" density="42.45" occupancy="7.04" waitingTime="0.00" speed="18.43" departed="0" arrived="0" entered="232" left="240" laneChangedFrom="139" laneChangedTo="139"/>
        <edge id="link3" sampledSeconds="13626.91" traveltime="54.51" overlapTraveltime="54.78" density="45.42" occupancy="7.53" waitingTime="0.00" speed="18.35" departed="0" arrived="0" entered="240" left="236" laneChangedFrom="129" laneChangedTo="129"/>
        <edge id="link4" sampledSeconds="12849.89" traveltime="54.07" overlapTraveltime="54.34" density="42.83" occupancy="7.10" waitingTime="0.00" speed="18.50" departed="0" arrived="0" entered="236" left="251" laneChangedFrom="134" laneChangedTo="134"/>
        <edge id="link5" sampledSeconds="13820.07" traveltime="54.41" overlapTraveltime="54.68" density="46.07" occupancy="7.66" waitingTime="0.00" speed="18.38" departed="0" arrived="257" entered="251" left="0" laneChangedFrom="128" laneChangedTo="128"/>
    </interval>
    <interval begin="600.00" end="900.00" id="ed1">
        <edge id="link1" sampledSeconds="13098.52" traveltime="53.55" overlapTraveltime="53.82" density="43.66" occupancy="7.26" waitingTime="0.00" speed="18.67" departed="246" arrived="0" entered="0" left="244" laneChangedFrom="204" laneChangedTo="204"/>
        <edge id="link2" sampledSeconds="13116.45" traveltime="53.62" overlapTraveltime="53.89" density="43.72" occupancy="7.25" waitingTime="0.00" speed="18.65" departed="0" arrived="0" entered="244" left="241" laneChangedFrom="131" laneChangedTo="131"/>
        <edge id="link3" sampledSeconds="12459.22" traveltime="53.21" overlapTraveltime="53.48" density="41.53" occupancy="6.89" waitingTime="0.00" speed="18.79" departed="0" arrived="0" entered="241" left="230" laneChangedFrom="167" laneChangedTo="167"/>
        <edge id="link4" sampledSeconds="12632.75" traveltime="53.06" overlapTraveltime="53.32" density="42.11" occupancy="6.98" waitingTime="0.00" speed="18.85" departed="0" arrived="0" entered="230" left="240" laneChangedFrom="134" laneChangedTo="134"/>
        <edge id="link5" sampledSeconds="12647.86" traveltime="53.08" overlapTraveltime="53.34" density="42.16" occupancy="7.01" waitingTime="0.00" speed="18.84" departed="0" arrived="237" entered="240" left="0" laneChangedFrom="140" laneChangedTo="140"/>
    </interval>
    <interval begin="900.00" end="1200.00" id="ed1">
        <edge id="link1" sampledSeconds="13179.33" traveltime="54.91" overlapTraveltime="55.18" density="43.93" occupancy="7.30" waitingTime="0.00" speed="18.21" departed="249" arrived="0" entered="0" left="238" laneChangedFrom="225" laneChangedTo="225"/>
        <edge id="link2" sampledSeconds="12724.02" traveltime="54.41" overlapTraveltime="54.68" density="42.41" occupancy="7.03" waitingTime="0.00" speed="18.38" departed="0" arrived="0" entered="238" left="228" laneChangedFrom="138" laneChangedTo="138"/>
        <edge id="link3" sampledSeconds="12882.69" traveltime="54.35" overlapTraveltime="54.62" density="42.94" occupancy="7.12" waitingTime="0.00" speed="18.40" departed="0" arrived="0" entered="228" left="244" laneChangedFrom="155" laneChangedTo="155"/>
        <edge id="link4" sampledSeconds="12978.96" traveltime="54.44" overlapTraveltime="54.71" density="43.26" occupancy="7.17" waitingTime="0.00" speed="18.37" departed="0" arrived="0" entered="244" left="237" laneChangedFrom="129" laneChangedTo="129"/>
        <edge id="link5" sampledSeconds="12298.20" traveltime="53.66" overlapTraveltime="53.93" density="40.99" occupancy="6.81" waitingTime="0.00" speed="18.64" departed="0" arrived="232" entered="237" left="0" laneChangedFrom="156" laneChangedTo="156"/>
    </interval>
    <interval begin="1200.00" end="1500.00" id="ed1">
        <edge id="link1" sampledSeconds="14873.59" traveltime="53.94" overlapTraveltime="54.21" density="49.58" occupancy="8.24" waitingTime="0.00" speed="18.54" departed="267" arrived="0" entered="0" left="277" laneChangedFrom="236" laneChangedTo="236"/>
        <edge id="link2" sampledSeconds="15165.82" traveltime="54.57" overlapTraveltime="54.84" density="50.55" occupancy="8.38" waitingTime="0.00" speed="18.33" departed="0" arrived="0" entered="277" left="279" laneChangedFrom="131" laneChangedTo="131"/>
        <edge id="link3" sampledSeconds="14892.17" traveltime="54.46" overlapTraveltime="54.73" density="49.64" occupancy="8.23" waitingTime="0.00" speed="18.36" departed="0" arrived="0" entered="279" left="273" laneChangedFrom="152" laneChangedTo="152"/>
        <edge id="link4" sampledSeconds="14756.13" traveltime="54.44" overlapTraveltime="54.71" density="49.19" occupancy="8.16" waitingTime="0.00" speed="18.37" departed="0" arrived="0" entered="273" left="256" laneChangedFrom="141" laneChangedTo="141"/>
        <edge id="link5" sampledSeconds="14545.61" traveltime="54.74" overlapTraveltime="55.02" density="48.49" occupancy="8.06" waitingTime="0.00" speed="18.27" departed="0" arrived="262" entered="256" left="0" laneChangedFrom="133" laneChangedTo="133"/>
    </interval>
    <interval begin="1500.00" end="1800.00" id="ed1">
        <edge id="link1" sampledSeconds="13942.42" traveltime="54.78" overlapTraveltime="55.05" density="46.47" occupancy="7.73" waitingTime="0.00" speed="18.26" departed="252" arrived="0" entered="0" left="265" laneChangedFrom="210" laneChangedTo="210"/>
        <edge id="link2" sampledSeconds="14918.31" traveltime="54.35" overlapTraveltime="54.62" density="49.73" occupancy="8.25" waitingTime="0.00" speed="18.40" departed="0" arrived="0" entered="265" left="268" laneChangedFrom="151" laneChangedTo="151"/>
        <edge id="link3" sampledSeconds="14989.56" traveltime="54.24" overlapTraveltime="54.51" density="49.97" occupancy="8.29" waitingTime="0.00" speed="18.44" departed="0" arrived="0" entered="268" left="272" laneChangedFrom="138" laneChangedTo="138"/>
        <edge id="link4" sampledSeconds="14523.59" traveltime="53.81" overlapTraveltime="54.08" density="48.41" occupancy="8.03" waitingTime="0.00" speed="18.58" departed="0" arrived="0" entered="272" left="268" laneChangedFrom="144" laneChangedTo="144"/>
        <edge id="link5" sampledSeconds="14000.70" traveltime="53.37" overlapTraveltime="53.63" density="46.67" occupancy="7.76" waitingTime="0.00" speed="18.74" departed="0" arrived="262" entered="268" left="0" laneChangedFrom="126" laneChangedTo="126"/>
    </interval>
    <interval begin="1800.00" end="2100.00" id="ed1">
        <edge id="link1" sampledSeconds="12330.17" traveltime="54.08" overlapTraveltime="54.35" density="41.10" occupancy="6.83" waitingTime="0.00" speed="18.49" departed="232" arrived="0" entered="0" left="216" laneChangedFrom="207" laneChangedTo="207"/>
        <edge id="link2" sampledSeconds="11457.77" traveltime="54.02" overlapTraveltime="54.29" density="38.19" occupancy="6.33" waitingTime="0.00" speed="18.51" departed="0" arrived="0" entered="216" left="210" laneChangedFrom="117" laneChangedTo="117"/>
        <edge id="link3" sampledSeconds="11764.72" traveltime="53.94" overlapTraveltime="54.21" density="39.22" occupancy="6.50" waitingTime="0.00" speed="18.54" departed="0" arrived="0" entered="210" left="227" laneChangedFrom="141" laneChangedTo="141"/>
        <edge id="link4" sampledSeconds="12664.88" traveltime="54.37" overlapTraveltime="54.64" density="42.22" occupancy="7.00" waitingTime="0.00" speed="18.39" departed="0" arrived="0" entered="227" left="241" laneChangedFrom="119" laneChangedTo="119"/>
        <edge id="link5" sampledSeconds="13398.12" traveltime="54.15" overlapTraveltime="54.42" density="44.66" occupancy="7.42" waitingTime="0.00" speed="18.47" departed="0" arrived="242" entered="241" left="0" laneChangedFrom="118" laneChangedTo="118"/>
    </interval>
    <interval begin="2100.00" end="2400.00" id="ed1">
        <edge id="link1" sampledSeconds="13029.63" traveltime="54.44" overlapTraveltime="54.72" density="43.43" occupancy="7.22" waitingTime="0.00" speed="18.37" departed="242" arrived="0" entered="0" left="251" laneChangedFrom="217" laneChangedTo="217"/>
        <edge id="link2" sampledSeconds="13971.95" traveltime="55.12" overlapTraveltime="55.39" density="46.57" occupancy="7.72" waitingTime="0.00" speed="18.14" departed="0" arrived="0" entered="251" left="258" laneChangedFrom="124" laneChangedTo="124"/>
        <edge id="link3" sampledSeconds="14078.40" traveltime="55.49" overlapTraveltime="55.76" density="46.93" occupancy="7.78" waitingTime="0.00" speed="18.02" departed="0" arrived="0" entered="258" left="240" laneChangedFrom="103" laneChangedTo="103"/>
        <edge id="link4" sampledSeconds="13072.43" traveltime="55.06" overlapTraveltime="55.33" density="43.57" occupancy="7.23" waitingTime="0.00" speed="18.16" departed="0" arrived="0" entered="240" left="231" laneChangedFrom="114" laneChangedTo="114"/>
        <edge id="link5" sampledSeconds="12144.48" traveltime="54.23" overlapTraveltime="54.50" density="40.48" occupancy="6.73" waitingTime="0.00" speed="18.44" departed="0" arrived="236" entered="231" left="0" laneChangedFrom="127" laneChangedTo="127"/>
    </interval>
    <interval begin="2400.00" end="2700.00" id="ed1">
        <edge id="link1" sampledSeconds="13103.92" traveltime="54.50" overlapTraveltime="54.77" density="43.68" occupancy="7.26" waitingTime="0.00" speed="18.35" departed="238" arrived="0" entered="0" left="238" laneChangedFrom="206" laneChangedTo="206"/>
        <edge id="link2" sampledSeconds="13060.01" traveltime="54.26" overlapTraveltime="54.53" density="43.53" occupancy="7.22" waitingTime="0.00" speed="18.43" departed="0" arrived="0" entered="238" left="244" laneChangedFrom="150" laneChangedTo="150"/>
        <edge id="link3" sampledSeconds="13086.09" traveltime="54.13" overlapTraveltime="54.40" density="43.62" occupancy="7.23" waitingTime="0.00" speed="18.47" departed="0" arrived="0" entered="244" left="249" laneChangedFrom="139" laneChangedTo="139"/>
        <edge id="link4" sampledSeconds="13178.35" traveltime="53.41" overlapTraveltime="53.67" density="43.93" occupancy="7.28" waitingTime="0.00" speed="18.72" departed="0" arrived="0" entered="249" left="251" laneChangedFrom="135" laneChangedTo="135"/>
        <edge id="link5" sampledSeconds="13355.26" traveltime="52.94" overlapTraveltime="53.20" density="44.52" occupancy="7.40" waitingTime="0.00" speed="18.89" departed="0" arrived="247" entered="251" left="0" laneChangedFrom="131" laneChangedTo="131"/>
    </interval>
    <interval begin="2700.00" end="3000.00" id="ed1">
        <edge id="link1" sampledSeconds="13539.65" traveltime="54.35" overlapTraveltime="54.62" density="45.13" occupancy="7.50" waitingTime="0.00" speed="18.40" departed="249" arrived="0" entered="0" left="248" laneChangedFrom="213" laneChangedTo="213"/>
        <edge id="link2" sampledSeconds="13788.61" traveltime="54.78" overlapTraveltime="55.05" density="45.96" occupancy="7.62" waitingTime="0.00" speed="18.25" departed="0" arrived="0" entered="248" left="250" laneChangedFrom="158" laneChangedTo="158"/>
        <edge id="link3" sampledSeconds="13727.45" traveltime="54.97" overlapTraveltime="55.24" density="45.76" occupancy="7.59" waitingTime="0.00" speed="18.19" departed="0" arrived="0" entered="250" left="250" laneChangedFrom="147" laneChangedTo="147"/>
        <edge id="link4" sampledSeconds="14115.47" traveltime="55.17" overlapTraveltime="55.44" density="47.05" occupancy="7.81" waitingTime="0.00" speed="18.13" departed="0" arrived="0" entered="250" left="235" laneChangedFrom="135" laneChangedTo="135"/>
        <edge id="link5" sampledSeconds="13179.17" traveltime="54.42" overlapTraveltime="54.69" density="43.93" occupancy="7.30" waitingTime="0.00" speed="18.37" departed="0" arrived="236" entered="235" left="0" laneChangedFrom="128" laneChangedTo="128"/>
    </interval>
    <interval begin="3000.00" end="3300.00" id="ed1">
        <edge id="link1" sampledSeconds="11798.88" traveltime="54.57" overlapTraveltime="54.85" density="39.33" occupancy="6.54" waitingTime="0.00" speed="18.32" departed="215" arrived="0" entered="0" left="211" laneChangedFrom="185" laneChangedTo="185"/>
        <edge id="link2" sampledSeconds="11404.56" traveltime="54.36" overlapTraveltime="54.63" density="38.02" occupancy="6.30" waitingTime="0.00" speed="18.40" departed="0" arrived="0" entered="211" left="207" laneChangedFrom="133" laneChangedTo="133"/>
        <edge id="link3" sampledSeconds="11948.14" traveltime="54.29" overlapTraveltime="54.56" density="39.83" occupancy="6.61" waitingTime="0.00" speed="18.42" departed="0" arrived="0" entered="207" left="221" laneChangedFrom="129" laneChangedTo="129"/>
        <edge id="link4" sampledSeconds="11939.03" traveltime="54.28" overlapTraveltime="54.55" density="39.80" occupancy="6.60" waitingTime="0.00" speed="18.42" departed="0" arrived="0" entered="221" left="237" laneChangedFrom="115" laneChangedTo="115"/>
        <edge id="link5" sampledSeconds="12992.81" traveltime="54.14" overlapTraveltime="54.41" density="43.31" occupancy="7.20" waitingTime="0.00" speed="18.47" departed="0" arrived="244" entered="237" left="0" laneChangedFrom="129" laneChangedTo="129"/>
    </interval>
    <interval begin="3300.00" end="3600.00" id="ed1">
        <edge id="link1" sampledSeconds="13947.80" traveltime="53.35" overlapTraveltime="53.62" density="46.49" occupancy="7.73" waitingTime="0.00" speed="18.74" departed="267" arrived="0" entered="0" left="266" laneChangedFrom="227" laneChangedTo="227"/>
        <edge id="link2" sampledSeconds="14355.54" traveltime="53.63" overlapTraveltime="53.90" density="47.85" occupancy="7.94" waitingTime="0.00" speed="18.65" departed="0" arrived="0" entered="266" left="253" laneChangedFrom="125" laneChangedTo="125"/>
        <edge id="link3" sampledSeconds="13302.57" traveltime="53.61" overlapTraveltime="53.88" density="44.34" occupancy="7.35" waitingTime="0.00" speed="18.65" departed="0" arrived="0" entered="253" left="246" laneChangedFrom="131" laneChangedTo="131"/>
        <edge id="link4" sampledSeconds="12661.14" traveltime="53.64" overlapTraveltime="53.91" density="42.20" occupancy="7.00" waitingTime="0.00" speed="18.64" departed="0" arrived="0" entered="246" left="229" laneChangedFrom="126" laneChangedTo="126"/>
        <edge id="link5" sampledSeconds="12201.01" traveltime="53.32" overlapTraveltime="53.59" density="40.67" occupancy="6.76" waitingTime="0.00" speed="18.75" departed="0" arrived="233" entered="229" left="0" laneChangedFrom="129" laneChangedTo="129"/>
    </interval>
</meandata>
